clearbot.py
clearbot-0.3.0.dist-info/LICENSE
clearbot-0.3.0.dist-info/METADATA
clearbot-0.3.0.dist-info/WHEEL
clearbot-0.3.0.dist-info/entry_points.txt
clearbot-0.3.0.dist-info/RECORD
