Metadata-Version: 2.1
Name: clearbot
Version: 0.3.0
Summary: Clearbit Logo API client
License: MIT
Author: Alban Siffer
Author-email: alban.siffer@irisa.fr
Requires-Python: >=3.10,<4.0
Classifier: License :: OSI Approved :: MIT License
Classifier: Programming Language :: Python :: 3
Classifier: Programming Language :: Python :: 3.10
Classifier: Programming Language :: Python :: 3.11
Requires-Dist: loguru (>=0.6.0,<0.7.0)
Requires-Dist: pillow (>=9.4.0,<10.0.0)
Requires-Dist: requests (>=2.28.2,<3.0.0)
